database/__init__.py
database/__main__.py
database/backends/mongo.py
database/backends/mssql.py
database/backends/mysql.py
database/backends/oracle.py
database/backends/postgres.py
database/backends/sqlite.py
database/backends/timescale.py
database/cache/memory.py
database/cache/redis.py
database/core/cache.py
database/core/database.py
database/core/schema.py
glean_database-0.3.0.dist-info/METADATA
glean_database-0.3.0.dist-info/WHEEL
glean_database-0.3.0.dist-info/entry_points.txt
glean_database-0.3.0.dist-info/top_level.txt
glean_database-0.3.0.dist-info/RECORD
