Metadata-Version: 2.4
Name: glean-database
Version: 0.3.0
Summary: Database access classes with caching capabilities
Requires-Python: >=3.12
Requires-Dist: click>=8.0.0
Provides-Extra: sqlite
Requires-Dist: aiosqlite>=0.19.0; extra == "sqlite"
Provides-Extra: postgres
Requires-Dist: asyncpg>=0.28.0; extra == "postgres"
Provides-Extra: mongo
Requires-Dist: motor>=3.3.0; extra == "mongo"
Provides-Extra: timescale
Requires-Dist: asyncpg>=0.28.0; extra == "timescale"
Provides-Extra: mysql
Requires-Dist: aiomysql>=0.2.0; extra == "mysql"
Provides-Extra: mssql
Requires-Dist: pymssql>=2.2.0; extra == "mssql"
Provides-Extra: oracle
Requires-Dist: oracledb>=2.0.0; extra == "oracle"
Provides-Extra: redis
Requires-Dist: redis[hiredis]>=5.0.0; extra == "redis"
Provides-Extra: all
Requires-Dist: aiosqlite>=0.19.0; extra == "all"
Requires-Dist: asyncpg>=0.28.0; extra == "all"
Requires-Dist: motor>=3.3.0; extra == "all"
Requires-Dist: aiomysql>=0.2.0; extra == "all"
Requires-Dist: pymssql>=2.2.0; extra == "all"
Requires-Dist: oracledb>=2.0.0; extra == "all"
Requires-Dist: redis[hiredis]>=5.0.0; extra == "all"
Provides-Extra: dev
Requires-Dist: pytest>=7.0.0; extra == "dev"
Requires-Dist: pytest-asyncio>=0.21.0; extra == "dev"
Requires-Dist: pytest-cov>=4.1.0; extra == "dev"
Requires-Dist: coverage>=7.3.0; extra == "dev"
Requires-Dist: mypy>=1.0.0; extra == "dev"
Requires-Dist: black>=22.0.0; extra == "dev"
Requires-Dist: isort>=5.0.0; extra == "dev"
Requires-Dist: pytest-cov>=4.1.0; extra == "dev"
